MANIFEST.in
README.rst
setup.py
pele_platform/__init__.py
pele_platform/main.py
pele_platform/Adaptive/__init__.py
pele_platform/Adaptive/simulation.py
pele_platform/Analysis/__init__.py
pele_platform/Analysis/pdf_report.py
pele_platform/Analysis/plots.py
pele_platform/Analysis/to_mae.py
pele_platform/Examples/test.sl
pele_platform/Examples/Adaptive/STR.rot.assign
pele_platform/Examples/Adaptive/adaptive.conf
pele_platform/Examples/Adaptive/pele_file_4Adaptive.conf
pele_platform/Examples/Adaptive/strz
pele_platform/Examples/Adaptive/test.sl
pele_platform/Examples/Msm/AS4_INIT.mae
pele_platform/Examples/Msm/PR_1A28_protein.pdb
pele_platform/Examples/Msm/PR_1A28_xray_-_minimized.pdb
pele_platform/Examples/Msm/PR_1A28_xray_-_minimized_processed.pdb
pele_platform/Examples/Msm/PR_AS4.pdb
pele_platform/Examples/Msm/input.yaml
pele_platform/Examples/analysis/input.yaml
pele_platform/Examples/analysis/input_flags.yaml
pele_platform/Examples/analysis/input_flags0.yaml
pele_platform/Examples/analysis/input_mae.yaml
pele_platform/Examples/bias/complex.pdb
pele_platform/Examples/bias/input.yaml
pele_platform/Examples/bias/input_defaults.yaml
pele_platform/Examples/constraints/input_external_constraints.yaml
pele_platform/Examples/constraints/input_ppp.pdb
pele_platform/Examples/constraints/input_ppp.yaml
pele_platform/Examples/exit/input.yaml
pele_platform/Examples/exit/input_defaults.yaml
pele_platform/Examples/exit_soft/input.yaml
pele_platform/Examples/exit_soft/input_defaults.yaml
pele_platform/Examples/flags/input.yaml
pele_platform/Examples/frag/1w7h_preparation_structure_2w.pdb
pele_platform/Examples/frag/1w7h_preparation_structure_2w_processed.pdb
pele_platform/Examples/frag/amino.pdb
pele_platform/Examples/frag/core.pdb
pele_platform/Examples/frag/input.yaml
pele_platform/Examples/frag/input_ai.yaml
pele_platform/Examples/frag/input_core.yaml
pele_platform/Examples/frag/input_core_sdf.yaml
pele_platform/Examples/frag/input_sim.yaml
pele_platform_test.egg-info/PKG-INFO
pele_platform_test.egg-info/SOURCES.txt
pele_platform_test.egg-info/dependency_links.txt
pele_platform_test.egg-info/requires.txt
pele_platform_test.egg-info/top_level.txt
