Metadata-Version: 1.0
Name: pele-platform-test
Version: 1.4.0
Summary: Automatic platform to launch PELE
Home-page: https://github.com/NostrumBioDiscovery/pele_platform
Author: Daniel Soler
Author-email: daniel.soler@nostrumbiodiscovery.com
License: UNKNOWN
Platform: UNKNOWN
